{
  "bids_meta": {
    "AccelNumReferenceLines": 32,
    "AccelerationFactorPE": 2,
    "AcquisitionMatrix": "0/256/256/0",
    "DeviceSerialNumber": "35426",
    "EchoTime": 0.00331,
    "EchoTrainLength": 1,
    "FlipAngle": 7,
    "ImageType": "ORIGINAL/PRIMARY/M/ND/NORM",
    "ImagingFrequency": 123191479,
    "InPlanePhaseEncodingDirection": "ROW",
    "InversionTime": 1.1,
    "MRAcquisitionType": "3D",
    "MagneticFieldStrength": 3,
    "ManufacturerModelName": "TrioTim",
    "NumberOfAverages": 1,
    "NumberOfPhaseEncodingSteps": 255,
    "PatientPosition": "HFS",
    "PercentPhaseFieldOfView": 100,
    "PercentSampling": 100,
    "PhaseEncodingDirection": "i-",
    "PixelBandwidth": 199,
    "ProtocolName": "MPRAGE - BWM",
    "ReceiveCoilName": "HeadMatrix",
    "RepetitionTime": 2.53,
    "ScanOptions": "IR",
    "ScanningSequence": "GR/IR",
    "SequenceName": "*tfl3d1_ns",
    "SequenceVariant": "SP/MP",
    "SoftwareVersions": "syngo MR B17",
    "TotalScanTimeSec": 363,
    "TransmitCoilName": "Body",
    "VariableFlipAngleFlag": "N",
    "dataset": "ds000030",
    "modality": "T1w",
    "subject_id": "70060"
  },
  "cjv": 0.445898301706568,
  "cnr": 2.968576915030256,
  "efc": 0.5326283021652685,
  "fber": 1213.4554443359375,
  "fwhm_avg": 3.1758229901884234,
  "fwhm_x": 3.26680897056527,
  "fwhm_y": 3.23594,
  "fwhm_z": 3.02472,
  "icvs_csf": 0.18776644050490202,
  "icvs_gm": 0.4190136939590619,
  "icvs_wm": 0.3932198655360361,
  "inu_med": 1.6990450620651245,
  "inu_range": 0.6029294252395632,
  "provenance": {
    "md5sum": "6e0cae02256d65f17ab934fd8f792984",
    "settings": {
      "testing": false
    },
    "software": "mriqc",
    "version": "21.0.0rc2",
    "warnings": {
      "large_rot_frame": true,
      "small_air_mask": false
    },
    "webapi_port": null,
    "webapi_url": "https://mriqc.nimh.nih.gov/api/v1"
  },
  "qi_1": 0.0,
  "qi_2": 0.0051011970794873065,
  "rpve_csf": 25.73440592723216,
  "rpve_gm": 12.58019340887007,
  "rpve_wm": 16.467350880319135,
  "size_x": 176,
  "size_y": 256,
  "size_z": 256,
  "snr_csf": 4.169651746284417,
  "snr_gm": 8.040192066296584,
  "snr_total": 9.787025772343412,
  "snr_wm": 17.151233504449234,
  "snrd_csf": 31.422003495164354,
  "snrd_gm": 46.7938392267529,
  "snrd_total": 48.687349560151006,
  "snrd_wm": 67.84620595853575,
  "spacing_x": 1.0000064373016357,
  "spacing_y": 1.0,
  "spacing_z": 1.0,
  "summary_bg_k": 49.14761373015828,
  "summary_bg_mad": 9.656191800893165,
  "summary_bg_mean": 16.710281372070312,
  "summary_bg_median": 12.974346160888672,
  "summary_bg_n": 3889052.0,
  "summary_bg_p05": 3.2003423094749452,
  "summary_bg_p95": 40.42082328796374,
  "summary_bg_stdv": 12.969539642333984,
  "summary_csf_k": 1.3615893901450118,
  "summary_csf_mad": 89.9970494506358,
  "summary_csf_mean": 451.23736572265625,
  "summary_csf_median": 463.1354675292969,
  "summary_csf_n": 9249.0,
  "summary_csf_p05": 236.07617797851563,
  "summary_csf_p95": 611.9842651367188,
  "summary_csf_stdv": 111.06693267822266,
  "summary_gm_k": 0.10081639805366738,
  "summary_gm_mad": 82.22343228872639,
  "summary_gm_mean": 693.14892578125,
  "summary_gm_median": 689.7041625976562,
  "summary_gm_n": 18497.0,
  "summary_gm_p05": 557.0794189453125,
  "summary_gm_p95": 841.2458862304687,
  "summary_gm_stdv": 85.77973175048828,
  "summary_wm_k": 0.4477306162951695,
  "summary_wm_mad": 56.13668248087091,
  "summary_wm_mean": 999.3985595703125,
  "summary_wm_median": 999.9993896484375,
  "summary_wm_n": 248200.0,
  "summary_wm_p05": 902.6655487060547,
  "summary_wm_p95": 1093.8306274414062,
  "summary_wm_stdv": 58.304691314697266,
  "tpm_overlap_csf": 0.14804787933826447,
  "tpm_overlap_gm": 0.4362161457538605,
  "tpm_overlap_wm": 0.5023412704467773,
  "wm2max": 0.7105466777281028
}