{
  "bids_meta": {
    "AccelNumReferenceLines": 32,
    "AccelerationFactorPE": 2,
    "AcquisitionMatrix": "0/256/256/0",
    "DeviceSerialNumber": "35343",
    "EchoTime": 0.00331,
    "EchoTrainLength": 1,
    "FlipAngle": 7,
    "ImageType": "ORIGINAL/PRIMARY/M/ND/NORM",
    "ImagingFrequency": 123227557,
    "InPlanePhaseEncodingDirection": "ROW",
    "InversionTime": 1.1,
    "MRAcquisitionType": "3D",
    "MagneticFieldStrength": 3,
    "ManufacturerModelName": "TrioTim",
    "NumberOfAverages": 1,
    "NumberOfPhaseEncodingSteps": 255,
    "PatientPosition": "HFS",
    "PercentPhaseFieldOfView": 100,
    "PercentSampling": 100,
    "PhaseEncodingDirection": "i-",
    "PixelBandwidth": 200,
    "ProtocolName": "MPRAGE - BWM",
    "ReceiveCoilName": "HeadMatrix",
    "RepetitionTime": 2.53,
    "ScanOptions": "IR",
    "ScanningSequence": "GR/IR",
    "SequenceName": "*tfl3d1_ns",
    "SequenceVariant": "SP/MP",
    "SoftwareVersions": "syngo MR B15",
    "TotalScanTimeSec": 363,
    "TransmitCoilName": "Body",
    "VariableFlipAngleFlag": "N",
    "dataset": "ds000030",
    "modality": "T1w",
    "subject_id": "10871"
  },
  "cjv": 0.40016116046013916,
  "cnr": 3.330108921189158,
  "efc": 0.5331251190997152,
  "fber": 1239.107666015625,
  "fwhm_avg": 3.160356666666667,
  "fwhm_x": 3.16299,
  "fwhm_y": 3.42019,
  "fwhm_z": 2.89789,
  "icvs_csf": 0.16608553664791698,
  "icvs_gm": 0.41841116665274347,
  "icvs_wm": 0.41550329669933955,
  "inu_med": 1.7635681629180908,
  "inu_range": 0.6956358313560478,
  "provenance": {
    "md5sum": "36605adcf13b0582415964b58c9a9c43",
    "settings": {
      "testing": false
    },
    "software": "mriqc",
    "version": "0.16.1",
    "warnings": {
      "large_rot_frame": true,
      "small_air_mask": false
    },
    "webapi_port": null,
    "webapi_url": "https://mriqc.nimh.nih.gov/api/v1"
  },
  "qi_1": 1.5675297410776768e-06,
  "qi_2": 0.0040490233034820395,
  "rpve_csf": 31.530048434146074,
  "rpve_gm": 13.81017588305524,
  "rpve_wm": 16.956763300753614,
  "size_x": 176,
  "size_y": 256,
  "size_z": 256,
  "snr_csf": 1.6538042482769792,
  "snr_gm": 8.141103104119418,
  "snr_total": 8.995825094174636,
  "snr_wm": 17.19256793012751,
  "snrd_csf": 18.33324816953782,
  "snrd_gm": 49.38987487840307,
  "snrd_total": 47.385181890289175,
  "snrd_wm": 74.43242262292664,
  "spacing_x": 1.0,
  "spacing_y": 1.0,
  "spacing_z": 1.0,
  "summary_bg_k": 180.18211488785371,
  "summary_bg_mad": 8.801740357150418,
  "summary_bg_mean": 17.200801849365234,
  "summary_bg_median": 14.579221725463867,
  "summary_bg_n": 4215191.0,
  "summary_bg_p05": 2.9048550128936768,
  "summary_bg_p95": 40.74612045288086,
  "summary_bg_stdv": 13.472867012023926,
  "summary_csf_k": -0.8868167223989198,
  "summary_csf_mad": 162.4462587533223,
  "summary_csf_mean": 288.160888671875,
  "summary_csf_median": 246.3067169189453,
  "summary_csf_n": 5588.0,
  "summary_csf_p05": 97.0162498474121,
  "summary_csf_p95": 539.2901062011717,
  "summary_csf_stdv": 148.9200897216797,
  "summary_gm_k": 0.3324285274229166,
  "summary_gm_mad": 79.12660889866243,
  "summary_gm_mean": 665.884521484375,
  "summary_gm_median": 663.5516967773438,
  "summary_gm_n": 12426.0,
  "summary_gm_p05": 537.6903076171875,
  "summary_gm_p95": 804.9153747558594,
  "summary_gm_stdv": 81.50308227539062,
  "summary_wm_k": 0.3816161219416174,
  "summary_wm_mad": 55.50600644560023,
  "summary_wm_mean": 998.8675537109375,
  "summary_wm_median": 999.9976806640625,
  "summary_wm_n": 236199.0,
  "summary_wm_p05": 900.889599609375,
  "summary_wm_p95": 1092.29052734375,
  "summary_wm_stdv": 58.16440963745117,
  "tpm_overlap_csf": 0.16029325127601624,
  "tpm_overlap_gm": 0.42615947127342224,
  "tpm_overlap_wm": 0.5068768262863159,
  "wm2max": 0.6678031649396485
}