{
  "bids_meta": {
    "AccelNumReferenceLines": 32,
    "AccelerationFactorPE": 2,
    "AcquisitionMatrix": "0/256/256/0",
    "DeviceSerialNumber": "35343",
    "EchoTime": 0.00331,
    "EchoTrainLength": 1,
    "FlipAngle": 7,
    "ImageType": "ORIGINAL/PRIMARY/M/ND/NORM",
    "ImagingFrequency": 123249659,
    "InPlanePhaseEncodingDirection": "ROW",
    "InversionTime": 1.1,
    "MRAcquisitionType": "3D",
    "MagneticFieldStrength": 3,
    "ManufacturerModelName": "TrioTim",
    "NumberOfAverages": 1,
    "NumberOfPhaseEncodingSteps": 255,
    "PatientPosition": "HFS",
    "PercentPhaseFieldOfView": 100,
    "PercentSampling": 100,
    "PhaseEncodingDirection": "i-",
    "PixelBandwidth": 200,
    "ProtocolName": "MPRAGE - BWM",
    "ReceiveCoilName": "HeadMatrix",
    "RepetitionTime": 2.53,
    "ScanOptions": "IR",
    "ScanningSequence": "GR/IR",
    "SequenceName": "*tfl3d1_ns",
    "SequenceVariant": "SP/MP",
    "SoftwareVersions": "syngo MR B15",
    "TotalScanTimeSec": 363,
    "TransmitCoilName": "Body",
    "VariableFlipAngleFlag": "N",
    "dataset": "ds000030",
    "modality": "T1w",
    "subject_id": "50008"
  },
  "cjv": 0.4775454445923474,
  "cnr": 2.861854684124095,
  "efc": 0.5604308397447081,
  "fber": 992.1312255859375,
  "fwhm_avg": 3.2396133333333332,
  "fwhm_x": 3.24816,
  "fwhm_y": 3.4067,
  "fwhm_z": 3.06398,
  "icvs_csf": 0.20557567717046307,
  "icvs_gm": 0.40774969082835777,
  "icvs_wm": 0.3866746320011792,
  "inu_med": 1.4624934196472168,
  "inu_range": 0.4377364635467529,
  "provenance": {
    "md5sum": "3f1a4e129668fae9a7e68c3dab4e18dd",
    "settings": {
      "testing": false
    },
    "software": "mriqc",
    "version": "0.16.1",
    "warnings": {
      "large_rot_frame": true,
      "small_air_mask": false
    },
    "webapi_port": null,
    "webapi_url": "https://mriqc.nimh.nih.gov/api/v1"
  },
  "qi_1": 1.878341183234195e-05,
  "qi_2": 0.00444625848874968,
  "rpve_csf": 29.615446232238693,
  "rpve_gm": 15.100258681612127,
  "rpve_wm": 18.982865349542564,
  "size_x": 176,
  "size_y": 256,
  "size_z": 256,
  "snr_csf": 2.1762047803916875,
  "snr_gm": 9.11476691454637,
  "snr_total": 8.967462825721055,
  "snr_wm": 15.611416782225103,
  "snrd_csf": 13.859942703289482,
  "snrd_gm": 33.53822221609679,
  "snrd_total": 31.58234126183066,
  "snrd_wm": 47.3488588661057,
  "spacing_x": 1.0,
  "spacing_y": 1.0,
  "spacing_z": 1.0,
  "summary_bg_k": 132.34382604775084,
  "summary_bg_mad": 13.836579589878006,
  "summary_bg_mean": 17.551481246948242,
  "summary_bg_median": 14.086199760437012,
  "summary_bg_n": 4218872.0,
  "summary_bg_p05": 0.0,
  "summary_bg_p95": 46.550809669494626,
  "summary_bg_stdv": 15.680933952331543,
  "summary_csf_k": -0.29708936173629885,
  "summary_csf_mad": 144.4870245419037,
  "summary_csf_mean": 309.185302734375,
  "summary_csf_median": 292.7240905761719,
  "summary_csf_n": 10221.0,
  "summary_csf_p05": 115.83313751220703,
  "summary_csf_p95": 547.4635620117188,
  "summary_csf_stdv": 134.50469970703125,
  "summary_gm_k": -0.08362200335482628,
  "summary_gm_mad": 77.89145393153034,
  "summary_gm_mean": 707.4169921875,
  "summary_gm_median": 708.3323364257812,
  "summary_gm_n": 11862.0,
  "summary_gm_p05": 579.7843933105469,
  "summary_gm_p95": 834.7627868652344,
  "summary_gm_stdv": 77.70933532714844,
  "summary_wm_k": 0.38179284880553377,
  "summary_wm_mad": 61.40030946725547,
  "summary_wm_mean": 1000.7556762695312,
  "summary_wm_median": 1000.0150756835938,
  "summary_wm_n": 187801.0,
  "summary_wm_p05": 896.6130981445312,
  "summary_wm_p95": 1106.85986328125,
  "summary_wm_stdv": 64.05648040771484,
  "tpm_overlap_csf": 0.1481059491634369,
  "tpm_overlap_gm": 0.4117874801158905,
  "tpm_overlap_wm": 0.4798099100589752,
  "wm2max": 0.6268405689320797
}