{
  "bids_meta": {
    "AccelNumReferenceLines": 32,
    "AccelerationFactorPE": 2,
    "AcquisitionMatrix": "0/256/256/0",
    "DeviceSerialNumber": "35343",
    "EchoTime": 0.00331,
    "EchoTrainLength": 1,
    "FlipAngle": 7,
    "ImageType": "ORIGINAL/PRIMARY/M/ND/NORM",
    "ImagingFrequency": 123227732,
    "InPlanePhaseEncodingDirection": "ROW",
    "InversionTime": 1.1,
    "MRAcquisitionType": "3D",
    "MagneticFieldStrength": 3,
    "ManufacturerModelName": "TrioTim",
    "NumberOfAverages": 1,
    "NumberOfPhaseEncodingSteps": 255,
    "PatientPosition": "HFS",
    "PercentPhaseFieldOfView": 100,
    "PercentSampling": 100,
    "PhaseEncodingDirection": "i-",
    "PixelBandwidth": 200,
    "ProtocolName": "MPRAGE - BWM",
    "ReceiveCoilName": "HeadMatrix",
    "RepetitionTime": 2.53,
    "ScanOptions": "IR",
    "ScanningSequence": "GR/IR",
    "SequenceName": "*tfl3d1_ns",
    "SequenceVariant": "SP/MP",
    "SoftwareVersions": "syngo MR B15",
    "TotalScanTimeSec": 363,
    "TransmitCoilName": "Body",
    "VariableFlipAngleFlag": "N",
    "dataset": "ds000030",
    "modality": "T1w",
    "subject_id": "60036"
  },
  "cjv": 0.4423845416104806,
  "cnr": 2.970015441827163,
  "efc": 0.49905946019099995,
  "fber": 1382.7852783203125,
  "fwhm_avg": 3.044403456244483,
  "fwhm_x": 3.09316036873345,
  "fwhm_y": 3.20229,
  "fwhm_z": 2.83776,
  "icvs_csf": 0.17602277982879658,
  "icvs_gm": 0.437906925669493,
  "icvs_wm": 0.3860702945017104,
  "inu_med": 1.8507895469665527,
  "inu_range": 0.5661576986312866,
  "provenance": {
    "md5sum": "4575a8dd857023ae08fc29ccd66be954",
    "settings": {
      "testing": false
    },
    "software": "mriqc",
    "version": "0.16.1",
    "warnings": {
      "large_rot_frame": true,
      "small_air_mask": false
    },
    "webapi_port": null,
    "webapi_url": "https://mriqc.nimh.nih.gov/api/v1"
  },
  "qi_1": 6.975647340073159e-06,
  "qi_2": 0.010289681449694891,
  "rpve_csf": 36.42150969876515,
  "rpve_gm": 16.350664254062675,
  "rpve_wm": 22.16760966865183,
  "size_x": 176,
  "size_y": 256,
  "size_z": 256,
  "snr_csf": 3.7332270516345063,
  "snr_gm": 8.472215494790355,
  "snr_total": 10.076222479011617,
  "snr_wm": 18.02322489060999,
  "snrd_csf": 29.664126079006785,
  "snrd_gm": 47.669946114998965,
  "snrd_total": 48.441018763024964,
  "snrd_wm": 67.98898409506913,
  "spacing_x": 0.9999998807907104,
  "spacing_y": 1.0,
  "spacing_z": 1.0,
  "summary_bg_k": 216.5392182434792,
  "summary_bg_mad": 9.63578540544011,
  "summary_bg_mean": 16.274934768676758,
  "summary_bg_median": 12.977231979370117,
  "summary_bg_n": 4199607.0,
  "summary_bg_p05": 3.2125637531280518,
  "summary_bg_p95": 38.74421691894531,
  "summary_bg_stdv": 14.094888687133789,
  "summary_csf_k": 0.7052988108818368,
  "summary_csf_mad": 93.22164593228484,
  "summary_csf_mean": 417.4444885253906,
  "summary_csf_median": 436.3017578125,
  "summary_csf_n": 4652.0,
  "summary_csf_p05": 179.7467498779297,
  "summary_csf_p95": 579.2058013916014,
  "summary_csf_stdv": 116.85730743408203,
  "summary_gm_k": 0.06742975614462088,
  "summary_gm_mad": 79.38030001924228,
  "summary_gm_mean": 704.0794067382812,
  "summary_gm_median": 701.1324462890625,
  "summary_gm_n": 11543.0,
  "summary_gm_p05": 570.5454284667969,
  "summary_gm_p95": 848.9995422363281,
  "summary_gm_stdv": 82.75309753417969,
  "summary_wm_k": 0.4201509578563556,
  "summary_wm_mad": 52.827929501223196,
  "summary_wm_mean": 998.8896484375,
  "summary_wm_median": 999.986083984375,
  "summary_wm_n": 175572.0,
  "summary_wm_p05": 905.6399536132812,
  "summary_wm_p95": 1087.875469970703,
  "summary_wm_stdv": 55.483036041259766,
  "tpm_overlap_csf": 0.15525107085704803,
  "tpm_overlap_gm": 0.4468798339366913,
  "tpm_overlap_wm": 0.509748637676239,
  "wm2max": 0.6623695334371908
}